py_bitflyer/__init__.py
py_bitflyer/api.py
py_bitflyer/exception.py
py_bitflyer/realtime_api.py
py_bitflyer-0.1.4.dist-info/LICENSE
py_bitflyer-0.1.4.dist-info/METADATA
py_bitflyer-0.1.4.dist-info/WHEEL
py_bitflyer-0.1.4.dist-info/top_level.txt
py_bitflyer-0.1.4.dist-info/RECORD
