Metadata-Version: 2.1
Name: py-bitflyer
Version: 0.1.4
Summary: A Python wrapper for bitFlyer API.
Home-page: https://github.com/py-bitflyer/py-bitflyer
License: MIT License
Keywords: bitflyer
Platform: UNKNOWN
Classifier: Programming Language :: Python :: 3
Classifier: License :: OSI Approved :: MIT License
Requires-Dist: requests
Requires-Dist: websocket-client
